hyperskill_python_portfolio/__init__.py
hyperskill_python_portfolio/_version.py
hyperskill_python_portfolio/billsplitter/__init__.py
hyperskill_python_portfolio/billsplitter/main.py
hyperskill_python_portfolio/chatbot/__init__.py
hyperskill_python_portfolio/chatbot/bot.py
hyperskill_python_portfolio/chatbot/main.py
hyperskill_python_portfolio/coffee_machine/__init__.py
hyperskill_python_portfolio/coffee_machine/machine.py
hyperskill_python_portfolio/coffee_machine/main.py
hyperskill_python_portfolio/coffee_machine/models.py
hyperskill_python_portfolio/currency_converter/__init__.py
hyperskill_python_portfolio/currency_converter/main.py
hyperskill_python_portfolio/hangman/README.md
hyperskill_python_portfolio/hangman/__init__.py
hyperskill_python_portfolio/hangman/game.py
hyperskill_python_portfolio/hangman/io_utils.py
hyperskill_python_portfolio/hangman/main.py
hyperskill_python_portfolio/hangman/models.py
hyperskill_python_portfolio/honest_calculator/__init__.py
hyperskill_python_portfolio/honest_calculator/main.py
hyperskill_python_portfolio/loancalc/README.md
hyperskill_python_portfolio/loancalc/__init__.py
hyperskill_python_portfolio/loancalc/cli.py
hyperskill_python_portfolio/loancalc/core.py
hyperskill_python_portfolio/loancalc/handlers.py
hyperskill_python_portfolio/loancalc/main.py
hyperskill_python_portfolio/loancalc/models.py
hyperskill_python_portfolio/rps/README.md
hyperskill_python_portfolio/rps/__init__.py
hyperskill_python_portfolio/rps/file_handler.py
hyperskill_python_portfolio/rps/game_logic.py
hyperskill_python_portfolio/rps/main.py
hyperskill_python_portfolio/zookeeper/__init__.py
hyperskill_python_portfolio/zookeeper/art.py
hyperskill_python_portfolio/zookeeper/main.py
hyperskill_python_portfolio-0.6.6.dist-info/licenses/LICENSE
hyperskill_python_portfolio-0.6.6.dist-info/METADATA
hyperskill_python_portfolio-0.6.6.dist-info/WHEEL
hyperskill_python_portfolio-0.6.6.dist-info/entry_points.txt
hyperskill_python_portfolio-0.6.6.dist-info/top_level.txt
hyperskill_python_portfolio-0.6.6.dist-info/RECORD
