Metadata-Version: 2.4
Name: hyperskill-python-portfolio
Version: 0.6.6
Summary: My journey through Hyperskill, captured in a portfolio of Python projects.
Author-email: Jegors Čemisovs <jegors.cemisovs@gmail.com>
License-Expression: MIT
Project-URL: Homepage, https://github.com/rabestro/hyperskill-python-portfolio
Project-URL: Repository, https://github.com/rabestro/hyperskill-python-portfolio.git
Project-URL: Issues, https://github.com/rabestro/hyperskill-python-portfolio/issues
Project-URL: Documentation, https://rabestro.github.io/hyperskill-python-portfolio/
Keywords: education,hyperskill
Classifier: Environment :: Console
Classifier: Intended Audience :: Developers
Classifier: Operating System :: OS Independent
Classifier: Programming Language :: Python :: 3
Classifier: Programming Language :: Python :: 3.12
Classifier: Programming Language :: Python :: 3.13
Classifier: Development Status :: 4 - Beta
Classifier: Topic :: Education
Requires-Python: >=3.12
License-File: LICENSE
Requires-Dist: requests
Provides-Extra: dev
Requires-Dist: ruff; extra == "dev"
Requires-Dist: mypy; extra == "dev"
Requires-Dist: radon; extra == "dev"
Requires-Dist: pytest; extra == "dev"
Requires-Dist: types-requests; extra == "dev"
Requires-Dist: poethepoet; extra == "dev"
Provides-Extra: docs
Requires-Dist: mkdocs; extra == "docs"
Requires-Dist: mkdocs-material; extra == "docs"
Requires-Dist: mkdocs-gen-files; extra == "docs"
Requires-Dist: mkdocs-literate-nav; extra == "docs"
Requires-Dist: mkdocstrings-python; extra == "docs"
Dynamic: license-file
